docs/source/conf.py
examples/ar.py
examples/nbeats.py
examples/nbeats_with_kan.py
examples/stallion.py
pytorch_forecasting/__init__.py
pytorch_forecasting/_registry/__init__.py
pytorch_forecasting/_registry/_lookup.py
pytorch_forecasting/base/__init__.py
pytorch_forecasting/base/_base_object.py
pytorch_forecasting/base/_base_pkg.py
pytorch_forecasting/callbacks/__init__.py
pytorch_forecasting/callbacks/predict.py
pytorch_forecasting/data/__init__.py
pytorch_forecasting/data/_tslib_data_module.py
pytorch_forecasting/data/data_module.py
pytorch_forecasting/data/encoders.py
pytorch_forecasting/data/examples.py
pytorch_forecasting/data/samplers.py
pytorch_forecasting/data/tests/__init__.py
pytorch_forecasting/data/tests/test_tslib_data_module.py
pytorch_forecasting/data/timeseries/__init__.py
pytorch_forecasting/data/timeseries/_timeseries.py
pytorch_forecasting/data/timeseries/_timeseries_v2.py
pytorch_forecasting/layers/__init__.py
pytorch_forecasting/layers/_attention/__init__.py
pytorch_forecasting/layers/_attention/_attention_layer.py
pytorch_forecasting/layers/_attention/_full_attention.py
pytorch_forecasting/layers/_blocks/__init__.py
pytorch_forecasting/layers/_blocks/_residual_block_dsipts.py
pytorch_forecasting/layers/_decomposition/__init__.py
pytorch_forecasting/layers/_decomposition/_series_decomp.py
pytorch_forecasting/layers/_embeddings/__init__.py
pytorch_forecasting/layers/_embeddings/_data_embedding.py
pytorch_forecasting/layers/_embeddings/_en_embedding.py
pytorch_forecasting/layers/_embeddings/_positional_embedding.py
pytorch_forecasting/layers/_embeddings/_sub_nn.py
pytorch_forecasting/layers/_encoders/__init__.py
pytorch_forecasting/layers/_encoders/_encoder.py
pytorch_forecasting/layers/_encoders/_encoder_layer.py
pytorch_forecasting/layers/_filter/__init__.py
pytorch_forecasting/layers/_filter/_moving_avg_filter.py
pytorch_forecasting/layers/_kan/__init__.py
pytorch_forecasting/layers/_kan/_kan_layer.py
pytorch_forecasting/layers/_kan/_utils.py
pytorch_forecasting-1.6.1.dist-info/licenses/LICENSE
pytorch_forecasting-1.6.1.dist-info/METADATA
pytorch_forecasting-1.6.1.dist-info/WHEEL
pytorch_forecasting-1.6.1.dist-info/top_level.txt
pytorch_forecasting-1.6.1.dist-info/RECORD
