Metadata-Version: 2.4
Name: pytorch-forecasting
Version: 1.6.1
Summary: Forecasting timeseries with PyTorch - dataloaders, normalizers, metrics and models
Author: Jan Beitner
Classifier: Intended Audience :: Developers
Classifier: Intended Audience :: Science/Research
Classifier: Programming Language :: Python :: 3
Classifier: Programming Language :: Python :: 3.10
Classifier: Programming Language :: Python :: 3.11
Classifier: Programming Language :: Python :: 3.12
Classifier: Programming Language :: Python :: 3.13
Classifier: Programming Language :: Python :: 3.14
Classifier: Topic :: Scientific/Engineering
Classifier: Topic :: Scientific/Engineering :: Mathematics
Classifier: Topic :: Scientific/Engineering :: Artificial Intelligence
Classifier: Topic :: Software Development
Classifier: Topic :: Software Development :: Libraries
Classifier: Topic :: Software Development :: Libraries :: Python Modules
Classifier: License :: OSI Approved :: MIT License
Requires-Python: <3.15,>=3.10
License-File: LICENSE
Requires-Dist: numpy<=3.0.0
Requires-Dist: torch!=2.0.1,<3.0.0,>=2.0.0
Requires-Dist: lightning<2.7.0,>=2.0.0
Requires-Dist: scipy<2.0,>=1.8
Requires-Dist: pandas<3.0.0,>=1.3.0
Requires-Dist: scikit-learn<2.0,>=1.2
Requires-Dist: scikit-base<0.14.0
Provides-Extra: all-extras
Requires-Dist: cpflows; extra == "all-extras"
Requires-Dist: matplotlib; extra == "all-extras"
Requires-Dist: optuna<5.0.0,>=3.1.0; extra == "all-extras"
Requires-Dist: optuna-integration; extra == "all-extras"
Requires-Dist: pytorch_optimizer<4.0.0,>=2.5.1; extra == "all-extras"
Requires-Dist: statsmodels; extra == "all-extras"
Provides-Extra: tuning
Requires-Dist: optuna<5.0.0,>=3.1.0; extra == "tuning"
Requires-Dist: optuna-integration; extra == "tuning"
Requires-Dist: statsmodels; extra == "tuning"
Provides-Extra: mqf2
Requires-Dist: cpflows; extra == "mqf2"
Provides-Extra: graph
Requires-Dist: networkx; extra == "graph"
Provides-Extra: dev
Requires-Dist: pydocstyle<7.0.0,>=6.1.1; extra == "dev"
Requires-Dist: pre-commit<5.0.0,>=3.2.0; extra == "dev"
Requires-Dist: invoke; extra == "dev"
Requires-Dist: mypy; extra == "dev"
Requires-Dist: pylint; extra == "dev"
Requires-Dist: ruff; extra == "dev"
Requires-Dist: pytest; extra == "dev"
Requires-Dist: pytest-xdist; extra == "dev"
Requires-Dist: pytest-cov; extra == "dev"
Requires-Dist: pytest-sugar; extra == "dev"
Requires-Dist: coverage; extra == "dev"
Requires-Dist: pyarrow; extra == "dev"
Requires-Dist: ipykernel; extra == "dev"
Requires-Dist: nbconvert; extra == "dev"
Requires-Dist: black[jupyter]; extra == "dev"
Requires-Dist: sphinx; extra == "dev"
Requires-Dist: pydata-sphinx-theme; extra == "dev"
Requires-Dist: nbsphinx; extra == "dev"
Requires-Dist: recommonmark; extra == "dev"
Requires-Dist: ipywidgets<9.0.0,>=8.0.1; extra == "dev"
Requires-Dist: pytest-dotenv<1.0.0,>=0.5.2; extra == "dev"
Requires-Dist: tensorboard<3.0.0,>=2.12.1; extra == "dev"
Requires-Dist: pandoc<3.0.0,>=2.3; extra == "dev"
Provides-Extra: docs
Requires-Dist: sphinx<9.1.1,>3.2; extra == "docs"
Requires-Dist: pydata-sphinx-theme; extra == "docs"
Requires-Dist: nbsphinx; extra == "docs"
Requires-Dist: pandoc; extra == "docs"
Requires-Dist: nbconvert; extra == "docs"
Requires-Dist: recommonmark; extra == "docs"
Requires-Dist: docutils; extra == "docs"
Provides-Extra: dependencies-2025
Requires-Dist: numpy==2.2.6; extra == "dependencies-2025"
Requires-Dist: torch==2.9.1; extra == "dependencies-2025"
Requires-Dist: lightning==2.5.6; extra == "dependencies-2025"
Requires-Dist: scipy==1.15.3; extra == "dependencies-2025"
Requires-Dist: pandas==2.3.3; extra == "dependencies-2025"
Requires-Dist: scikit-learn==1.7.2; extra == "dependencies-2025"
Requires-Dist: scikit-base==0.13.0; extra == "dependencies-2025"
Provides-Extra: github-actions
Requires-Dist: pytest-github-actions-annotate-failures; extra == "github-actions"
Dynamic: license-file
